README.rst
disentangler.py
setup.py
disentangler.egg-info/PKG-INFO
disentangler.egg-info/SOURCES.txt
disentangler.egg-info/dependency_links.txt
disentangler.egg-info/top_level.txt